corellia_preprocessor/__init__.py
corellia_preprocessor/operations.py
corellia_preprocessor/preprocessor.py
corellia_preprocessor-1.0.3.dist-info/METADATA
corellia_preprocessor-1.0.3.dist-info/WHEEL
corellia_preprocessor-1.0.3.dist-info/top_level.txt
corellia_preprocessor-1.0.3.dist-info/RECORD
