Metadata-Version: 2.1
Name: corellia-preprocessor
Version: 1.0.3
Summary: Corellia data market Preprocessor package
Home-page: UNKNOWN
Author: Boris Vasilev
Author-email: borisvasilev395@gmail.com
License: MIT
Platform: UNKNOWN
Requires-Dist: bleach (==3.3.0)
Requires-Dist: certifi (==2020.12.5)
Requires-Dist: cffi (==1.14.5)
Requires-Dist: chardet (==4.0.0)
Requires-Dist: colorama (==0.4.4)
Requires-Dist: cryptography (==3.4.7)
Requires-Dist: docutils (==0.17)
Requires-Dist: idna (==2.10)
Requires-Dist: importlib-metadata (==3.10.0)
Requires-Dist: jeepney (==0.6.0)
Requires-Dist: joblib (==1.0.1)
Requires-Dist: keyring (==23.0.1)
Requires-Dist: numpy (==1.19.5)
Requires-Dist: packaging (==20.9)
Requires-Dist: pandas (==1.2.3)
Requires-Dist: pkginfo (==1.7.0)
Requires-Dist: pycparser (==2.20)
Requires-Dist: Pygments (==2.8.1)
Requires-Dist: pyparsing (==2.4.7)
Requires-Dist: python-dateutil (==2.8.1)
Requires-Dist: pytz (==2021.1)
Requires-Dist: readme-renderer (==29.0)
Requires-Dist: requests (==2.25.1)
Requires-Dist: requests-toolbelt (==0.9.1)
Requires-Dist: rfc3986 (==1.4.0)
Requires-Dist: ruamel.yaml (==0.17.2)
Requires-Dist: ruamel.yaml.clib (==0.2.2)
Requires-Dist: scikit-learn (==0.24.1)
Requires-Dist: scipy (==1.6.2)
Requires-Dist: SecretStorage (==3.3.1)
Requires-Dist: six (==1.15.0)
Requires-Dist: threadpoolctl (==2.1.0)
Requires-Dist: tqdm (==4.60.0)
Requires-Dist: twine (==3.4.1)
Requires-Dist: urllib3 (==1.26.4)
Requires-Dist: webencodings (==0.5.1)
Requires-Dist: zipp (==3.4.1)
